{
  "main": {
    "id": "5c95d0b8c05781b6",
    "type": "split",
    "children": [
      {
        "id": "89005f85024e0cd7",
        "type": "tabs",
        "children": [
          {
            "id": "a34258f0d53024c5",
            "type": "leaf",
            "state": {
              "type": "markdown",
              "state": {
                "file": "1주차.md",
                "mode": "source",
                "source": false
              }
            }
          }
        ]
      }
    ],
    "direction": "vertical"
  },
  "left": {
    "id": "6afc1be7c145d56e",
    "type": "split",
    "children": [
      {
        "id": "3e695ef6eec22dab",
        "type": "tabs",
        "children": [
          {
            "id": "df62a4f7898a56d2",
            "type": "leaf",
            "state": {
              "type": "file-explorer",
              "state": {
                "sortOrder": "alphabetical"
              }
            }
          },
          {
            "id": "0b1778c836e95ac6",
            "type": "leaf",
            "state": {
              "type": "search",
              "state": {
                "query": "",
                "matchingCase": false,
                "explainSearch": false,
                "collapseAll": false,
                "extraContext": false,
                "sortOrder": "alphabetical"
              }
            }
          },
          {
            "id": "05a10540bf2c4fe7",
            "type": "leaf",
            "state": {
              "type": "bookmarks",
              "state": {}
            }
          }
        ]
      }
    ],
    "direction": "horizontal",
    "width": 300
  },
  "right": {
    "id": "23b2c89b3655a20f",
    "type": "split",
    "children": [
      {
        "id": "497c2cf6715117af",
        "type": "tabs",
        "children": [
          {
            "id": "c11a2a9ac743610a",
            "type": "leaf",
            "state": {
              "type": "backlink",
              "state": {
                "file": "1주차.md",
                "collapseAll": false,
                "extraContext": false,
                "sortOrder": "alphabetical",
                "showSearch": false,
                "searchQuery": "",
                "backlinkCollapsed": false,
                "unlinkedCollapsed": true
              }
            }
          },
          {
            "id": "4a1cfca1ef6fa773",
            "type": "leaf",
            "state": {
              "type": "outgoing-link",
              "state": {
                "file": "1주차.md",
                "linksCollapsed": false,
                "unlinkedCollapsed": true
              }
            }
          },
          {
            "id": "1d2e63eaf6c4965c",
            "type": "leaf",
            "state": {
              "type": "tag",
              "state": {
                "sortOrder": "frequency",
                "useHierarchy": true
              }
            }
          },
          {
            "id": "c0d37cbeb7494cc9",
            "type": "leaf",
            "state": {
              "type": "outline",
              "state": {
                "file": "1주차.md"
              }
            }
          }
        ]
      }
    ],
    "direction": "horizontal",
    "width": 300,
    "collapsed": true
  },
  "left-ribbon": {
    "hiddenItems": {
      "switcher:퀵 스위처 열기": false,
      "graph:그래프 뷰 열기": false,
      "canvas:새 캔버스 만들기": false,
      "daily-notes:오늘의 데일리 노트 열기": false,
      "templates:템플릿 삽입": false,
      "command-palette:명령어 팔레트 열기": false
    }
  },
  "active": "a34258f0d53024c5",
  "lastOpenFiles": [
    "1주차.md"
  ]
}